invenio_stats/__init__.py
invenio_stats/aggregations.py
invenio_stats/bookmark.py
invenio_stats/cli.py
invenio_stats/config.py
invenio_stats/errors.py
invenio_stats/ext.py
invenio_stats/processors.py
invenio_stats/proxies.py
invenio_stats/queries.py
invenio_stats/queues.py
invenio_stats/receivers.py
invenio_stats/tasks.py
invenio_stats/templates.py
invenio_stats/utils.py
invenio_stats/views.py
invenio_stats/contrib/__init__.py
invenio_stats/contrib/config.py
invenio_stats/contrib/event_builders.py
invenio_stats/contrib/aggregations/__init__.py
invenio_stats/contrib/aggregations/aggr_file_download/__init__.py
invenio_stats/contrib/aggregations/aggr_file_download/os-v1/__init__.py
invenio_stats/contrib/aggregations/aggr_file_download/os-v1/aggr-file-download-v1.json
invenio_stats/contrib/aggregations/aggr_file_download/os-v2/__init__.py
invenio_stats/contrib/aggregations/aggr_file_download/os-v2/aggr-file-download-v1.json
invenio_stats/contrib/aggregations/aggr_file_download/v7/__init__.py
invenio_stats/contrib/aggregations/aggr_file_download/v7/aggr-file-download-v1.json
invenio_stats/contrib/aggregations/aggr_record_view/__init__.py
invenio_stats/contrib/aggregations/aggr_record_view/os-v1/__init__.py
invenio_stats/contrib/aggregations/aggr_record_view/os-v1/aggr-record-view-v1.json
invenio_stats/contrib/aggregations/aggr_record_view/os-v2/__init__.py
invenio_stats/contrib/aggregations/aggr_record_view/os-v2/aggr-record-view-v1.json
invenio_stats/contrib/aggregations/aggr_record_view/v7/__init__.py
invenio_stats/contrib/aggregations/aggr_record_view/v7/aggr-record-view-v1.json
invenio_stats/contrib/file_download/__init__.py
invenio_stats/contrib/file_download/os-v1/__init__.py
invenio_stats/contrib/file_download/os-v1/file-download-v1.json
invenio_stats/contrib/file_download/os-v2/__init__.py
invenio_stats/contrib/file_download/os-v2/file-download-v1.json
invenio_stats/contrib/file_download/v7/__init__.py
invenio_stats/contrib/file_download/v7/file-download-v1.json
invenio_stats-6.0.0.dist-info/licenses/AUTHORS.rst
invenio_stats-6.0.0.dist-info/licenses/LICENSE
invenio_stats-6.0.0.dist-info/METADATA
invenio_stats-6.0.0.dist-info/WHEEL
invenio_stats-6.0.0.dist-info/entry_points.txt
invenio_stats-6.0.0.dist-info/top_level.txt
invenio_stats-6.0.0.dist-info/RECORD
