Metadata-Version: 2.4
Name: invenio-stats
Version: 6.0.0
Summary: Invenio module for collecting statistics.
Home-page: https://github.com/inveniosoftware/invenio-stats
Author: CERN
Author-email: info@invenio-software.org
License: MIT
Keywords: invenio statistics
Platform: any
Classifier: Development Status :: 5 - Production/Stable
Requires-Python: >=3.7
License-File: LICENSE
License-File: AUTHORS.rst
Requires-Dist: counter-robots>=2018.6
Requires-Dist: invenio-base<3.0.0,>=2.0.0
Requires-Dist: invenio-cache<4.0.0,>=3.0.0
Requires-Dist: invenio-celery<3.0.0,>=2.0.0
Requires-Dist: invenio-queues>=1.0.0a2
Requires-Dist: maxminddb-geolite2>=2018.703
Requires-Dist: python-dateutil>=2.7.0
Requires-Dist: python-geoip>=1.2
Requires-Dist: invenio-i18n>=2.0.0
Provides-Extra: tests
Requires-Dist: pytest-black>=0.6.0; extra == "tests"
Requires-Dist: invenio-accounts<8.0.0,>=7.0.0; extra == "tests"
Requires-Dist: invenio-app<4.0.0,>=3.0.0; extra == "tests"
Requires-Dist: invenio-db[postgresql]<3.0.0,>=2.2.0; extra == "tests"
Requires-Dist: invenio-files-rest<5.0.0,>=4.0.0; extra == "tests"
Requires-Dist: invenio-records<5.0.0,>=4.0.0; extra == "tests"
Requires-Dist: invenio-records-ui<4.0.0,>=3.0.0; extra == "tests"
Requires-Dist: pytest-invenio<5.0.0,>=4.0.0; extra == "tests"
Requires-Dist: Sphinx>=5; extra == "tests"
Provides-Extra: elasticsearch7
Requires-Dist: invenio-search[elasticsearch7]<4.0.0,>=3.0.0; extra == "elasticsearch7"
Provides-Extra: opensearch1
Requires-Dist: invenio-search[opensearch1]<4.0.0,>=3.0.0; extra == "opensearch1"
Provides-Extra: opensearch2
Requires-Dist: invenio-search[opensearch2]<4.0.0,>=3.0.0; extra == "opensearch2"
Provides-Extra: docs
Dynamic: license-file
